mtg_proxy_printer/__init__.py
mtg_proxy_printer/__main__.py
mtg_proxy_printer/app_dirs.py
mtg_proxy_printer/application.py
mtg_proxy_printer/argument_parser.py
mtg_proxy_printer/carddb_migrations.py
mtg_proxy_printer/http_file.py
mtg_proxy_printer/logger.py
mtg_proxy_printer/meta_data.py
mtg_proxy_printer/metered_file.py
mtg_proxy_printer/missing_images_manager.py
mtg_proxy_printer/natsort.py
mtg_proxy_printer/print.py
mtg_proxy_printer/progress_meter.py
mtg_proxy_printer/save_file_migrations.py
mtg_proxy_printer/settings.py
mtg_proxy_printer/sqlite_helpers.py
mtg_proxy_printer/units_and_sizes.py
mtg_proxy_printer/async_tasks/__init__.py
mtg_proxy_printer/async_tasks/base.py
mtg_proxy_printer/async_tasks/card_info_downloader.py
mtg_proxy_printer/async_tasks/decklist_downloader.py
mtg_proxy_printer/async_tasks/document_loader.py
mtg_proxy_printer/async_tasks/downloader_base.py
mtg_proxy_printer/async_tasks/image_downloader.py
mtg_proxy_printer/async_tasks/print_count_updater.py
mtg_proxy_printer/async_tasks/printing_filter_updater.py
mtg_proxy_printer/async_tasks/update_checker.py
mtg_proxy_printer/decklist_parser/__init__.py
mtg_proxy_printer/decklist_parser/common.py
mtg_proxy_printer/decklist_parser/csv_parsers.py
mtg_proxy_printer/decklist_parser/re_parsers.py
mtg_proxy_printer/document_controller/__init__.py
mtg_proxy_printer/document_controller/_interface.py
mtg_proxy_printer/document_controller/card_actions.py
mtg_proxy_printer/document_controller/compact_document.py
mtg_proxy_printer/document_controller/edit_custom_card.py
mtg_proxy_printer/document_controller/edit_document_settings.py
mtg_proxy_printer/document_controller/import_deck_list.py
mtg_proxy_printer/document_controller/load_document.py
mtg_proxy_printer/document_controller/move_cards.py
mtg_proxy_printer/document_controller/move_page.py
mtg_proxy_printer/document_controller/new_document.py
mtg_proxy_printer/document_controller/page_actions.py
mtg_proxy_printer/document_controller/replace_card.py
mtgproxyprinter-0.35.0.dist-info/licenses/LICENSE.md
mtgproxyprinter-0.35.0.dist-info/licenses/doc/ThirdPartyLicenses.md
mtgproxyprinter-0.35.0.dist-info/METADATA
mtgproxyprinter-0.35.0.dist-info/WHEEL
mtgproxyprinter-0.35.0.dist-info/entry_points.txt
mtgproxyprinter-0.35.0.dist-info/top_level.txt
mtgproxyprinter-0.35.0.dist-info/RECORD
