Metadata-Version: 2.4
Name: MTGProxyPrinter
Version: 0.35.0
Summary: MTGProxyPrinter allows efficient printing of Magic: The Gathering cards for playtesting purposes.
Author-email: Thomas Hess <thomas.hess@udo.edu>
License-Expression: GPL-3.0-or-later
Project-URL: Homepage, https://chiselapp.com/user/luziferius/repository/MTGProxyPrinter/index
Project-URL: Issues, https://chiselapp.com/user/luziferius/repository/MTGProxyPrinter/ticket
Project-URL: Changelog, https://chiselapp.com/user/luziferius/repository/MTGProxyPrinter/doc/trunk/doc/changelog.md
Project-URL: Translations, https://crowdin.com/project/mtgproxyprinter
Project-URL: Repository, https://chiselapp.com/user/luziferius/repository/MTGProxyPrinter/timeline
Project-URL: Github, https://github.com/luziferius/MTGProxyPrinter/
Project-URL: funding, https://ko-fi.com/luziferius
Keywords: MTG,Magic The Gathering,Printing,Proxies
Classifier: Development Status :: 4 - Beta
Classifier: Environment :: X11 Applications :: Qt
Classifier: Environment :: Win32 (MS Windows)
Classifier: Intended Audience :: End Users/Desktop
Classifier: Natural Language :: English
Classifier: Operating System :: OS Independent
Classifier: Programming Language :: Python :: 3.11
Classifier: Programming Language :: Python :: 3.12
Classifier: Programming Language :: Python :: 3.13
Classifier: Programming Language :: Python :: 3 :: Only
Classifier: Topic :: Games/Entertainment :: Board Games
Classifier: Topic :: Internet :: WWW/HTTP :: Indexing/Search
Requires-Python: !=3.11.1,<4,>=3.11
License-File: LICENSE.md
License-File: doc/ThirdPartyLicenses.md
Requires-Dist: platformdirs>=2.6.0
Requires-Dist: PySide6_Essentials>=6.7.0
Requires-Dist: ijson>=3.2.0
Requires-Dist: ijson>=3.2.1; python_version >= "3.12"
Requires-Dist: Pint>=0.22
Requires-Dist: delegateto==1.5
Requires-Dist: PyHamcrest>=2
Requires-Dist: truststore
Provides-Extra: dev
Requires-Dist: pytest>=6.0; extra == "dev"
Requires-Dist: pytest-cov; extra == "dev"
Requires-Dist: pytest-timeout; extra == "dev"
Requires-Dist: pytest-qt>=4.5; extra == "dev"
Requires-Dist: tox>=4.0; extra == "dev"
Requires-Dist: pillow; platform_system == "Windows" and extra == "dev"
Provides-Extra: package
Requires-Dist: build; extra == "package"
Requires-Dist: cx_Freeze>=7.2; platform_python_implementation == "CPython" and extra == "package"
Requires-Dist: pillow; platform_system == "Windows" and extra == "package"
Dynamic: license-file
